.coveragerc
.gitignore
.travis.yml
CHANGELOG.md
COPYING
LICENSE
README.md
appveyor.yml
pylintrc
requirements.txt
setup.cfg
setup.py
test_requirements.txt
aloe/__init__.py
aloe/codegen.py
aloe/exceptions.py
aloe/fs.py
aloe/parser.py
aloe/plugin.py
aloe/registry.py
aloe/result.py
aloe/runner.py
aloe/strings.py
aloe/testclass.py
aloe/testing.py
aloe/tools.py
aloe/utils.py
aloe.egg-info/PKG-INFO
aloe.egg-info/SOURCES.txt
aloe.egg-info/dependency_links.txt
aloe.egg-info/entry_points.txt
aloe.egg-info/requires.txt
aloe.egg-info/top_level.txt
aloe/steps/__init__.py
aloe/steps/factoryboy.py
aloe_sphinx/__init__.py
aloe_sphinx/autosteps.py
aloe_sphinx/gherkindomain.py
docs/Makefile
docs/aloe.rst
docs/classes.rst
docs/conf.py
docs/extending.rst
docs/extras.rst
docs/features.rst
docs/getting-started.rst
docs/hooks.rst
docs/index.rst
docs/links.rst
docs/porting.rst
docs/steps.rst
docs/world.rst
tests/__init__.py
tests/utils.py
tests/bad_steps_app/__init__.py
tests/bad_steps_app/features/dummy.feature
tests/bad_steps_app/features/steps/__init__.py
tests/bad_steps_app_2/__init__.py
tests/bad_steps_app_2/features/__init__.py
tests/bad_steps_app_2/features/dummy.feature
tests/bad_steps_app_2/features/steps.py
tests/callbacks_app/__init__.py
tests/callbacks_app/features/__init__.py
tests/callbacks_app/features/all_callbacks_1.feature
tests/callbacks_app/features/all_callbacks_2.feature
tests/callbacks_app/features/behave_as.feature
tests/callbacks_app/features/behave_as_ru.feature
tests/callbacks_app/features/example_callbacks.feature
tests/callbacks_app/features/feature_callbacks_1.feature
tests/callbacks_app/features/feature_callbacks_2.feature
tests/callbacks_app/features/step_callbacks.feature
tests/callbacks_app/features/step_failed.feature
tests/callbacks_app/features/steps.py
tests/callbacks_app/features/testcase_methods.feature
tests/factoryboy_app/__init__.py
tests/factoryboy_app/features/__init__.py
tests/factoryboy_app/features/bad.feature
tests/factoryboy_app/features/good.feature
tests/factoryboy_app/features/steps.py
tests/functional/__init__.py
tests/functional/test_callbacks.py
tests/functional/test_factoryboy.py
