Metadata-Version: 1.1
Name: aloe
Version: 0.1.18
Summary: Gherkin runner compatible with Lettuce
Home-page: https://github.com/aloetesting/aloe
Author: Alexey Kotlyarov
Author-email: a@koterpillar.com
License: UNKNOWN
Platform: UNKNOWN
Classifier: License :: OSI Approved :: GNU General Public License v3 or later (GPLv3+)
Classifier: Programming Language :: Python
Classifier: Programming Language :: Python :: 2
Classifier: Programming Language :: Python :: 3
